isic_cli/__init__.py
isic_cli/oauth.py
isic_cli/session.py
isic_cli/cli/__init__.py
isic_cli/cli/__main__.py
isic_cli/cli/accession.py
isic_cli/cli/collection.py
isic_cli/cli/context.py
isic_cli/cli/image.py
isic_cli/cli/metadata.py
isic_cli/cli/types.py
isic_cli/cli/user.py
isic_cli/cli/utils.py
isic_cli/io/__init__.py
isic_cli/io/http.py
isic_cli/utils/__init__.py
isic_cli/utils/version.py
isic_cli-12.4.0.dist-info/licenses/LICENSE
tests/__init__.py
tests/conftest.py
tests/test_cli_base.py
tests/test_cli_collection.py
tests/test_cli_image.py
tests/test_cli_metadata.py
tests/test_user.py
tests/test_utils.py
tests/test_version.py
isic_cli-12.4.0.dist-info/METADATA
isic_cli-12.4.0.dist-info/WHEEL
isic_cli-12.4.0.dist-info/entry_points.txt
isic_cli-12.4.0.dist-info/top_level.txt
isic_cli-12.4.0.dist-info/RECORD
