Metadata-Version: 2.4
Name: isic-cli
Version: 12.4.0
Home-page: https://github.com/ImageMarkup/isic-cli
Author: Kitware, Inc.
Author-email: kitware@kitware.com
License: Apache 2.0
Project-URL: Bug Reports, https://github.com/ImageMarkup/isic-cli/issues
Project-URL: Source, https://github.com/ImageMarkup/isic-cli
Classifier: Development Status :: 3 - Alpha
Classifier: Environment :: Web Environment
Classifier: Intended Audience :: Developers
Classifier: License :: OSI Approved :: Apache Software License
Classifier: Operating System :: OS Independent
Classifier: Programming Language :: Python :: 3
Classifier: Programming Language :: Python :: 3.10
Classifier: Programming Language :: Python :: 3.11
Classifier: Programming Language :: Python :: 3.12
Classifier: Programming Language :: Python :: 3.13
Classifier: Programming Language :: Python
Requires-Python: >=3.10
License-File: LICENSE
Requires-Dist: click>=8.2.0
Requires-Dist: django-s3-file-field-client>=1.0.0
Requires-Dist: girder-cli-oauth-client<1.0.0
Requires-Dist: humanize
Requires-Dist: isic-metadata>=1.2.0
Requires-Dist: more-itertools
Requires-Dist: packaging
Requires-Dist: requests
Requires-Dist: retryable-requests
Requires-Dist: rich
Requires-Dist: sentry-sdk
Requires-Dist: tenacity
Provides-Extra: dev
Requires-Dist: ipython; extra == "dev"
Requires-Dist: tox; extra == "dev"
Dynamic: author
Dynamic: author-email
Dynamic: classifier
Dynamic: description
Dynamic: description-content-type
Dynamic: home-page
Dynamic: keywords
Dynamic: license
Dynamic: license-file
Dynamic: project-url
Dynamic: provides-extra
Dynamic: requires-dist
Dynamic: requires-python
